cson_to_markdown/__init__.py
cson_to_markdown/__main__.py
cson_to_markdown/config.py
cson_to_markdown/extractor.py
cson_to_markdown/file_converter.py
cson_to_markdown/writer.py
cson_to_markdown-0.1.3.dist-info/entry_points.txt
cson_to_markdown-0.1.3.dist-info/LICENSE
cson_to_markdown-0.1.3.dist-info/WHEEL
cson_to_markdown-0.1.3.dist-info/METADATA
cson_to_markdown-0.1.3.dist-info/RECORD
